envsafe/__init__.py
envsafe/core.py
envsafe/exceptions.py
envsafe/loaders.py
envsafe/parsers.py
envsafe-0.1.1.dist-info/licenses/LICENSE
envsafe-0.1.1.dist-info/METADATA
envsafe-0.1.1.dist-info/WHEEL
envsafe-0.1.1.dist-info/RECORD
