Metadata-Version: 2.4
Name: envsafe
Version: 0.1.1
Summary: Type-safe environment variables with automatic .env loading
License: MIT
License-File: LICENSE
Author: Rajarshi Datta
Author-email: rayan05rio@gmail.com
Requires-Python: >=3.11,<4.0
Classifier: License :: OSI Approved :: MIT License
Classifier: Programming Language :: Python :: 3
Classifier: Programming Language :: Python :: 3.11
Classifier: Programming Language :: Python :: 3.12
Classifier: Programming Language :: Python :: 3.13
Classifier: Programming Language :: Python :: 3.14
Requires-Dist: python-dotenv (>=1.0,<2.0)
